{
  "count": 6,
  "accounts": [
    {
      "user_id": "17354181",
      "username": "23232323234",
      "normalized_username": "23232323234",
      "suspicion_score": 5,
      "patterns": {
        "ends_with_numbers": true,
        "contains_bot_keywords": false,
        "repeated_patterns": true,
        "sequential_numbers": true,
        "many_numbers": true,
        "special_word_combos": false,
        "generic_names": false,
        "consecutive_duplicates": false
      },
      "user_data": {
        "latest": {
          "rank": 1765800,
          "score": 3730,
          "username": "23232323234",
          "level": 0,
          "id": 17354181,
          "friend_images": {
            "micro": "https://www.kogstatic.com/gen_cache/avatar_images/panda_18x18.jpg",
            "small": "https://www.kogstatic.com/gen_cache/avatar_images/panda_46x46.jpg",
            "medium": "https://www.kogstatic.com/gen_cache/avatar_images/panda_64x64.jpg",
            "large": "https://www.kogstatic.com/gen_cache/avatar_images/panda_330x451.jpg"
          },
          "is_subscriber": 0
        },
        "pages": [
          4415
        ],
        "meta": {
          "batch": "1765001to1770000"
        }
      }
    },
    {
      "user_id": "7966551",
      "username": "232323225",
      "normalized_username": "232323225",
      "suspicion_score": 3,
      "patterns": {
        "ends_with_numbers": true,
        "contains_bot_keywords": false,
        "repeated_patterns": true,
        "sequential_numbers": false,
        "many_numbers": true,
        "special_word_combos": false,
        "generic_names": false,
        "consecutive_duplicates": false
      },
      "user_data": {
        "latest": {
          "rank": 1892843,
          "score": 3406,
          "username": "232323225",
          "level": 0,
          "id": 7966551,
          "friend_images": {
            "micro": "https://www.kogstatic.com/placeholder/blockboy_micro_18x18.jpg",
            "small": "https://www.kogstatic.com/placeholder/blockboy_small_46x46.jpg",
            "medium": "https://www.kogstatic.com/placeholder/blockboy_medium_64x64.jpg",
            "large": "https://www.kogstatic.com/placeholder/blockboy_large_330x451.jpg"
          },
          "is_subscriber": 0
        },
        "pages": [
          4733
        ],
        "meta": {
          "batch": "1890001to1895000"
        }
      }
    },
    {
      "user_id": "20687193",
      "username": "2323232323232233",
      "normalized_username": "2323232323232233",
      "suspicion_score": 3,
      "patterns": {
        "ends_with_numbers": true,
        "contains_bot_keywords": false,
        "repeated_patterns": true,
        "sequential_numbers": false,
        "many_numbers": true,
        "special_word_combos": false,
        "generic_names": false,
        "consecutive_duplicates": false
      },
      "user_data": {
        "latest": {
          "rank": 1955593,
          "score": 3260,
          "username": "2323232323232233",
          "level": 0,
          "id": 20687193,
          "friend_images": {
            "micro": "https://www.kogstatic.com/gen_cache/avatar_images/robot_18x18.jpg",
            "small": "https://www.kogstatic.com/gen_cache/avatar_images/robot_46x46.jpg",
            "medium": "https://www.kogstatic.com/gen_cache/avatar_images/robot_64x64.jpg",
            "large": "https://www.kogstatic.com/gen_cache/avatar_images/robot_330x451.jpg"
          },
          "is_subscriber": 0
        },
        "pages": [
          4889
        ],
        "meta": {
          "batch": "1955001to1960000"
        }
      }
    },
    {
      "user_id": "20701223",
      "username": "232323232323223",
      "normalized_username": "232323232323223",
      "suspicion_score": 3,
      "patterns": {
        "ends_with_numbers": true,
        "contains_bot_keywords": false,
        "repeated_patterns": true,
        "sequential_numbers": false,
        "many_numbers": true,
        "special_word_combos": false,
        "generic_names": false,
        "consecutive_duplicates": false
      },
      "user_data": {
        "latest": {
          "rank": 1981418,
          "score": 3203,
          "username": "232323232323223",
          "level": 0,
          "id": 20701223,
          "friend_images": {
            "micro": "https://www.kogstatic.com/gen_cache/avatar_images/panda_18x18.jpg",
            "small": "https://www.kogstatic.com/gen_cache/avatar_images/panda_46x46.jpg",
            "medium": "https://www.kogstatic.com/gen_cache/avatar_images/panda_64x64.jpg",
            "large": "https://www.kogstatic.com/gen_cache/avatar_images/panda_330x451.jpg"
          },
          "is_subscriber": 0
        },
        "pages": [
          4954
        ],
        "meta": {
          "batch": "1980001to1985000"
        }
      }
    },
    {
      "user_id": "16467011",
      "username": "2323236623",
      "normalized_username": "2323236623",
      "suspicion_score": 3,
      "patterns": {
        "ends_with_numbers": true,
        "contains_bot_keywords": false,
        "repeated_patterns": true,
        "sequential_numbers": false,
        "many_numbers": true,
        "special_word_combos": false,
        "generic_names": false,
        "consecutive_duplicates": false
      },
      "user_data": {
        "latest": {
          "rank": 1994597,
          "score": 3175,
          "username": "2323236623",
          "level": 0,
          "id": 16467011,
          "friend_images": {
            "micro": "https://www.kogstatic.com/gen_cache/avatar_images/panda_18x18.jpg",
            "small": "https://www.kogstatic.com/gen_cache/avatar_images/panda_46x46.jpg",
            "medium": "https://www.kogstatic.com/gen_cache/avatar_images/panda_64x64.jpg",
            "large": "https://www.kogstatic.com/gen_cache/avatar_images/panda_330x451.jpg"
          },
          "is_subscriber": 0
        },
        "pages": [
          4987
        ],
        "meta": {
          "batch": "1990001to1995000"
        }
      }
    },
    {
      "user_id": "20422892",
      "username": "232323554",
      "normalized_username": "232323554",
      "suspicion_score": 3,
      "patterns": {
        "ends_with_numbers": true,
        "contains_bot_keywords": false,
        "repeated_patterns": true,
        "sequential_numbers": false,
        "many_numbers": true,
        "special_word_combos": false,
        "generic_names": false,
        "consecutive_duplicates": false
      },
      "user_data": {
        "latest": {
          "rank": 2116094,
          "score": 2930,
          "username": "232323554",
          "level": 0,
          "id": 20422892,
          "friend_images": {
            "micro": "https://www.kogstatic.com/placeholder/blockboy_micro_18x18.jpg",
            "small": "https://www.kogstatic.com/placeholder/blockboy_small_46x46.jpg",
            "medium": "https://www.kogstatic.com/placeholder/blockboy_medium_64x64.jpg",
            "large": "https://www.kogstatic.com/placeholder/blockboy_large_330x451.jpg"
          },
          "is_subscriber": 0
        },
        "pages": [
          5291
        ],
        "meta": {
          "batch": "2115001to2120000"
        }
      }
    }
  ]
}