{
  "count": 2,
  "accounts": [
    {
      "user_id": "24031766",
      "username": "44444558487564",
      "normalized_username": "44444558487564",
      "suspicion_score": 3,
      "patterns": {
        "ends_with_numbers": true,
        "contains_bot_keywords": false,
        "repeated_patterns": false,
        "sequential_numbers": false,
        "many_numbers": true,
        "special_word_combos": false,
        "generic_names": false,
        "consecutive_duplicates": true
      },
      "user_data": {
        "latest": {
          "rank": 1269818,
          "score": 5640,
          "username": "44444558487564",
          "level": 0,
          "id": 24031766,
          "friend_images": {
            "micro": "https://www.kogstatic.com/placeholder/blockboy_micro_18x18.jpg",
            "small": "https://www.kogstatic.com/placeholder/blockboy_small_46x46.jpg",
            "medium": "https://www.kogstatic.com/placeholder/blockboy_medium_64x64.jpg",
            "large": "https://www.kogstatic.com/placeholder/blockboy_large_330x451.jpg"
          },
          "is_subscriber": 0
        },
        "pages": [
          3175
        ],
        "meta": {
          "batch": "1265001to1270000"
        }
      }
    },
    {
      "user_id": "668121334",
      "username": "444445555558284379014307825",
      "normalized_username": "444445555558284379014307825",
      "suspicion_score": 4,
      "patterns": {
        "ends_with_numbers": true,
        "contains_bot_keywords": false,
        "repeated_patterns": true,
        "sequential_numbers": false,
        "many_numbers": true,
        "special_word_combos": false,
        "generic_names": false,
        "consecutive_duplicates": true
      },
      "user_data": {
        "latest": {
          "rank": 1290022,
          "score": 5530,
          "username": "444445555558284379014307825",
          "level": 0,
          "id": 668121334,
          "friend_images": {
            "micro": "https://www.kogstatic.com/gen_cache/avatar_images/girl_18x18.jpg",
            "small": "https://www.kogstatic.com/gen_cache/avatar_images/girl_46x46.jpg",
            "medium": "https://www.kogstatic.com/gen_cache/avatar_images/girl_64x64.jpg",
            "large": "https://www.kogstatic.com/gen_cache/avatar_images/girl_330x451.jpg"
          },
          "is_subscriber": 0
        },
        "pages": [
          3226
        ],
        "meta": {
          "batch": "1290001to1295000"
        }
      }
    }
  ]
}