{
  "count": 3,
  "accounts": [
    {
      "user_id": "16106716",
      "username": "natalia_hoe",
      "found_slurs": [
        "hoe"
      ],
      "user_data": {
        "latest": {
          "rank": 1517670,
          "score": 4530,
          "username": "natalia_hoe",
          "level": 0,
          "id": 16106716,
          "friend_images": {
            "micro": "https://www.kogstatic.com/gen_cache/avatar_images/girl_18x18.jpg",
            "small": "https://www.kogstatic.com/gen_cache/avatar_images/girl_46x46.jpg",
            "medium": "https://www.kogstatic.com/gen_cache/avatar_images/girl_64x64.jpg",
            "large": "https://www.kogstatic.com/gen_cache/avatar_images/girl_330x451.jpg"
          },
          "is_subscriber": 0
        },
        "pages": [
          3795
        ],
        "meta": {
          "batch": "1515001to1520000"
        }
      }
    },
    {
      "user_id": "20759305",
      "username": "jeff hoe dick",
      "found_slurs": [
        "dick",
        "hoe"
      ],
      "user_data": {
        "latest": {
          "rank": 1594632,
          "score": 4256,
          "username": "jeff hoe dick",
          "level": 0,
          "id": 20759305,
          "friend_images": {
            "micro": "https://www.kogstatic.com/gen_cache/avatar_images/kingoffire_18x18.jpg",
            "small": "https://www.kogstatic.com/gen_cache/avatar_images/kingoffire_46x46.jpg",
            "medium": "https://www.kogstatic.com/gen_cache/avatar_images/kingoffire_64x64.jpg",
            "large": "https://www.kogstatic.com/gen_cache/avatar_images/kingoffire_330x451.jpg"
          },
          "is_subscriber": 0
        },
        "pages": [
          3987
        ],
        "meta": {
          "batch": "1590001to1595000"
        }
      }
    },
    {
      "user_id": "51344628",
      "username": "Samoa Hoe",
      "found_slurs": [
        "hoe"
      ],
      "user_data": {
        "latest": {
          "rank": 1649271,
          "score": 4075,
          "username": "Samoa Hoe",
          "level": 0,
          "id": 51344628,
          "friend_images": {
            "micro": "https://www.kogstatic.com/gen_cache/avatar_images/robot_18x18.jpg",
            "small": "https://www.kogstatic.com/gen_cache/avatar_images/robot_46x46.jpg",
            "medium": "https://www.kogstatic.com/gen_cache/avatar_images/robot_64x64.jpg",
            "large": "https://www.kogstatic.com/gen_cache/avatar_images/robot_330x451.jpg"
          },
          "is_subscriber": 0
        },
        "pages": [
          4124
        ],
        "meta": {
          "batch": "1645001to1650000"
        }
      }
    }
  ]
}
