{
  "count": 4,
  "accounts": [
    {
      "user_id": "17739852",
      "username": "7878787878878787878",
      "normalized_username": "7878787878878787878",
      "suspicion_score": 3,
      "patterns": {
        "ends_with_numbers": true,
        "contains_bot_keywords": false,
        "repeated_patterns": true,
        "sequential_numbers": false,
        "many_numbers": true,
        "special_word_combos": false,
        "generic_names": false,
        "consecutive_duplicates": false
      },
      "user_data": {
        "latest": {
          "rank": 2127225,
          "score": 2910,
          "username": "7878787878878787878",
          "level": 0,
          "id": 17739852,
          "friend_images": {
            "micro": "https://www.kogstatic.com/placeholder/blockboy_micro_18x18.jpg",
            "small": "https://www.kogstatic.com/placeholder/blockboy_small_46x46.jpg",
            "medium": "https://www.kogstatic.com/placeholder/blockboy_medium_64x64.jpg",
            "large": "https://www.kogstatic.com/placeholder/blockboy_large_330x451.jpg"
          },
          "is_subscriber": 0
        },
        "pages": [
          5319
        ],
        "meta": {
          "batch": "2125001to2130000"
        }
      }
    },
    {
      "user_id": "24940580",
      "username": "78787878787878787878+9789",
      "normalized_username": "787878787878787878789789",
      "suspicion_score": 5,
      "patterns": {
        "ends_with_numbers": true,
        "contains_bot_keywords": false,
        "repeated_patterns": true,
        "sequential_numbers": true,
        "many_numbers": true,
        "special_word_combos": false,
        "generic_names": false,
        "consecutive_duplicates": false
      },
      "user_data": {
        "latest": {
          "rank": 2517294,
          "score": 2300,
          "username": "78787878787878787878+9789",
          "level": 0,
          "id": 24940580,
          "friend_images": {
            "micro": "https://www.kogstatic.com/placeholder/blockboy_micro_18x18.jpg",
            "small": "https://www.kogstatic.com/placeholder/blockboy_small_46x46.jpg",
            "medium": "https://www.kogstatic.com/placeholder/blockboy_medium_64x64.jpg",
            "large": "https://www.kogstatic.com/placeholder/blockboy_large_330x451.jpg"
          },
          "is_subscriber": 0
        },
        "pages": [
          6294
        ],
        "meta": {
          "batch": "2515001to2520000"
        }
      }
    },
    {
      "user_id": "16679832",
      "username": "78787877878",
      "normalized_username": "78787877878",
      "suspicion_score": 3,
      "patterns": {
        "ends_with_numbers": true,
        "contains_bot_keywords": false,
        "repeated_patterns": true,
        "sequential_numbers": false,
        "many_numbers": true,
        "special_word_combos": false,
        "generic_names": false,
        "consecutive_duplicates": false
      },
      "user_data": {
        "latest": {
          "rank": 2566706,
          "score": 2240,
          "username": "78787877878",
          "level": 0,
          "id": 16679832,
          "friend_images": {
            "micro": "https://www.kogstatic.com/gen_cache/db/33/db33e7d5-74eb-4f5d-8573-0acc81f52b21_18x18.jpg",
            "small": "https://www.kogstatic.com/gen_cache/db/33/db33e7d5-74eb-4f5d-8573-0acc81f52b21_46x46.jpg",
            "medium": "https://www.kogstatic.com/gen_cache/db/33/db33e7d5-74eb-4f5d-8573-0acc81f52b21_64x64.jpg",
            "large": "https://www.kogstatic.com/gen_cache/db/33/db33e7d5-74eb-4f5d-8573-0acc81f52b21_330x451.jpg"
          },
          "is_subscriber": 0
        },
        "pages": [
          6417
        ],
        "meta": {
          "batch": "2565001to2570000"
        }
      }
    },
    {
      "user_id": "17622450",
      "username": "787878787878787877",
      "normalized_username": "787878787878787877",
      "suspicion_score": 3,
      "patterns": {
        "ends_with_numbers": true,
        "contains_bot_keywords": false,
        "repeated_patterns": true,
        "sequential_numbers": false,
        "many_numbers": true,
        "special_word_combos": false,
        "generic_names": false,
        "consecutive_duplicates": false
      },
      "user_data": {
        "latest": {
          "rank": 2582641,
          "score": 2220,
          "username": "787878787878787877",
          "level": 0,
          "id": 17622450,
          "friend_images": {
            "micro": "https://www.kogstatic.com/gen_cache/avatar_images/kingoffire_18x18.jpg",
            "small": "https://www.kogstatic.com/gen_cache/avatar_images/kingoffire_46x46.jpg",
            "medium": "https://www.kogstatic.com/gen_cache/avatar_images/kingoffire_64x64.jpg",
            "large": "https://www.kogstatic.com/gen_cache/avatar_images/kingoffire_330x451.jpg"
          },
          "is_subscriber": 0
        },
        "pages": [
          6457
        ],
        "meta": {
          "batch": "2580001to2585000"
        }
      }
    }
  ]
}